{"v":"5.12.2","fr":25,"ip":0,"op":51,"w":2950,"h":2950,"nm":"39","assets":[],"layers":[{"ind":1,"ty":4,"nm":"Layer 2 Outlines","sr":1,"ks":{"o":{"a":0,"k":100},"r":{"a":1,"k":[{"i":{"x":[0.833],"y":[0.833]},"o":{"x":[0.167],"y":[0.167]},"t":0,"s":[0]},{"i":{"x":[0.833],"y":[0.833]},"o":{"x":[0.167],"y":[0.167]},"t":25,"s":[18]},{"t":50,"s":[-9]}]},"p":{"a":0,"k":[1432.599,1418.258,0],"l":2},"a":{"a":0,"k":[949.744,1154.401,0],"l":2},"s":{"a":0,"k":[89.674,89.674,100],"l":2}},"ao":0,"shapes":[{"ty":"gr","it":[{"ind":0,"ty":"sh","ks":{"a":0,"k":{"i":[[-8.898,0.769],[0,0],[-0.711,-8.218],[0,0],[8.218,-0.711],[0,0],[0.769,8.895],[0,0],[-2.177,2.85],[0.727,8.413],[0,0],[-2.175,2.856],[0.728,8.42],[0,0],[-2.175,2.856],[0.728,8.414],[0,0]],"o":[[0,0],[8.219,-0.711],[0,0],[0.711,8.219],[0,0],[-8.898,0.769],[0,0],[-0.332,-3.846],[-8.24,-0.015],[0,0],[-0.333,-3.846],[-8.239,-0.009],[0,0],[-0.333,-3.851],[-8.238,-0.015],[0,0],[-0.77,-8.901]],"v":[[-55.767,-52.022],[46.948,-60.904],[63.116,-47.31],[70.546,38.602],[56.952,54.771],[-13.298,60.845],[-30.806,46.122],[-30.911,44.918],[-27.935,34.487],[-43.996,19.646],[-44.1,18.441],[-41.128,8.004],[-57.19,-6.838],[-57.294,-8.036],[-54.321,-18.473],[-70.383,-33.315],[-70.487,-34.518]],"c":true}},"nm":"Path 1"},{"ty":"fl","c":{"a":0,"k":[0.957,0.788,0.6,1]},"o":{"a":0,"k":100},"r":1,"nm":"Fill 1"},{"ty":"tr","p":{"a":0,"k":[1808.398,808.673]},"a":{"a":0,"k":[0,0]},"s":{"a":0,"k":[100,100]},"r":{"a":0,"k":0},"o":{"a":0,"k":100},"sk":{"a":0,"k":0},"sa":{"a":0,"k":0},"nm":"Transform"}],"nm":"Group 1"},{"ty":"gr","it":[{"ind":0,"ty":"sh","ks":{"a":0,"k":{"i":[[8.922,-0.402],[0,0],[-0.372,-8.241],[0,0],[-8.241,0.372],[0,0],[0.402,8.919],[0,0],[2.531,2.54],[0.38,8.436],[0,0],[2.531,2.547],[0.38,8.442],[0,0],[2.53,2.547],[0.38,8.437],[0,0]],"o":[[0,0],[-8.241,0.371],[0,0],[0.372,8.241],[0,0],[8.922,-0.402],[0,0],[-0.174,-3.856],[8.166,-1.093],[0,0],[-0.173,-3.856],[8.167,-1.087],[0,0],[-0.174,-3.862],[8.165,-1.093],[0,0],[-0.403,-8.925]],"v":[[50.149,-60.299],[-52.846,-55.659],[-67.095,-40.065],[-63.215,46.08],[-47.621,60.329],[22.82,57.156],[38.249,40.268],[38.195,39.061],[33.88,29.109],[47.861,12.292],[47.806,11.085],[43.492,1.127],[57.474,-15.69],[57.42,-16.891],[53.106,-26.849],[67.087,-43.666],[67.033,-44.872]],"c":true}},"nm":"Path 1"},{"ty":"fl","c":{"a":0,"k":[0.957,0.788,0.6,1]},"o":{"a":0,"k":100},"r":1,"nm":"Fill 1"},{"ty":"tr","p":{"a":0,"k":[144.463,1189.585]},"a":{"a":0,"k":[0,0]},"s":{"a":0,"k":[100,100]},"r":{"a":0,"k":0},"o":{"a":0,"k":100},"sk":{"a":0,"k":0},"sa":{"a":0,"k":0},"nm":"Transform"}],"nm":"Group 2"},{"ty":"gr","it":[{"ind":0,"ty":"sh","ks":{"a":0,"k":{"i":[[4.632,0],[3.536,3.536],[0,0],[-7.072,7.072],[-7.072,-7.072],[0,0],[0,0],[-7.072,-7.072],[7.072,-7.072],[0,0]],"o":[[-4.632,0],[0,0],[-7.072,-7.072],[7.072,-7.072],[0,0],[0,0],[7.072,-7.072],[7.072,7.072],[0,0],[-3.536,3.536]],"v":[[-37.934,72.922],[-50.734,67.618],[-82.745,35.607],[-82.745,10.006],[-57.145,10.006],[-37.934,29.219],[57.145,-65.849],[82.745,-65.849],[82.745,-40.25],[-25.134,67.618]],"c":true}},"nm":"Path 1"},{"ty":"fl","c":{"a":0,"k":[0.42,0.416,0.427,1]},"o":{"a":0,"k":100},"r":1,"nm":"Fill 1"},{"ty":"tr","p":{"a":0,"k":[394.383,2018.351]},"a":{"a":0,"k":[0,0]},"s":{"a":0,"k":[100,100]},"r":{"a":0,"k":0},"o":{"a":0,"k":100},"sk":{"a":0,"k":0},"sa":{"a":0,"k":0},"nm":"Transform"}],"nm":"Group 3"},{"ty":"gr","it":[{"ind":0,"ty":"sh","ks":{"a":0,"k":{"i":[[0,0],[0,0],[0,0],[0,0]],"o":[[0,0],[0,0],[0,0],[0,0]],"v":[[-111.127,111.121],[111.126,111.121],[111.126,-111.12],[-111.127,-111.12]],"c":true}},"nm":"Path 1"},{"ind":1,"ty":"sh","ks":{"a":0,"k":{"i":[[0,0],[0,0],[0,0],[0,0]],"o":[[0,0],[0,0],[0,0],[0,0]],"v":[[147.333,147.327],[-147.334,147.327],[-147.334,-147.328],[147.333,-147.328]],"c":true}},"nm":"Path 2"},{"ty":"mm","mm":1,"nm":"Merge Paths 1"},{"ty":"fl","c":{"a":0,"k":[0.42,0.416,0.427,1]},"o":{"a":0,"k":100},"r":1,"nm":"Fill 1"},{"ty":"tr","p":{"a":0,"k":[394.384,2019.236]},"a":{"a":0,"k":[0,0]},"s":{"a":0,"k":[100,100]},"r":{"a":0,"k":0},"o":{"a":0,"k":100},"sk":{"a":0,"k":0},"sa":{"a":0,"k":0},"nm":"Transform"}],"nm":"Group 4"},{"ty":"gr","it":[{"ind":0,"ty":"sh","ks":{"a":0,"k":{"i":[[0,0],[0,0],[0,0],[0,0]],"o":[[0,0],[0,0],[0,0],[0,0]],"v":[[553.243,24.138],[-553.242,24.138],[-553.242,-24.138],[553.243,-24.138]],"c":true}},"nm":"Path 1"},{"ty":"fl","c":{"a":0,"k":[0.42,0.416,0.427,1]},"o":{"a":0,"k":100},"r":1,"nm":"Fill 1"},{"ty":"tr","p":{"a":0,"k":[1179.49,1896.046]},"a":{"a":0,"k":[0,0]},"s":{"a":0,"k":[100,100]},"r":{"a":0,"k":0},"o":{"a":0,"k":100},"sk":{"a":0,"k":0},"sa":{"a":0,"k":0},"nm":"Transform"}],"nm":"Group 5"},{"ty":"gr","it":[{"ind":0,"ty":"sh","ks":{"a":0,"k":{"i":[[0,0],[0,0],[0,0],[0,0]],"o":[[0,0],[0,0],[0,0],[0,0]],"v":[[560.776,24.138],[-560.776,24.138],[-560.776,-24.138],[560.776,-24.138]],"c":true}},"nm":"Path 1"},{"ty":"fl","c":{"a":0,"k":[0.42,0.416,0.427,1]},"o":{"a":0,"k":100},"r":1,"nm":"Fill 1"},{"ty":"tr","p":{"a":0,"k":[1187.024,2142.425]},"a":{"a":0,"k":[0,0]},"s":{"a":0,"k":[100,100]},"r":{"a":0,"k":0},"o":{"a":0,"k":100},"sk":{"a":0,"k":0},"sa":{"a":0,"k":0},"nm":"Transform"}],"nm":"Group 6"},{"ty":"gr","it":[{"ind":0,"ty":"sh","ks":{"a":0,"k":{"i":[[4.632,0],[3.536,3.536],[0,0],[-7.072,7.072],[-7.072,-7.072],[0,0],[0,0],[-7.072,-7.072],[7.072,-7.072],[0,0]],"o":[[-4.632,0],[0,0],[-7.072,-7.072],[7.072,-7.072],[0,0],[0,0],[7.072,-7.072],[7.072,7.072],[0,0],[-3.536,3.536]],"v":[[-37.934,72.922],[-50.734,67.618],[-82.745,35.607],[-82.745,10.007],[-57.145,10.007],[-37.934,29.219],[57.145,-65.849],[82.745,-65.849],[82.745,-40.249],[-25.134,67.618]],"c":true}},"nm":"Path 1"},{"ty":"fl","c":{"a":0,"k":[0.42,0.416,0.427,1]},"o":{"a":0,"k":100},"r":1,"nm":"Fill 1"},{"ty":"tr","p":{"a":0,"k":[394.383,1517.823]},"a":{"a":0,"k":[0,0]},"s":{"a":0,"k":[100,100]},"r":{"a":0,"k":0},"o":{"a":0,"k":100},"sk":{"a":0,"k":0},"sa":{"a":0,"k":0},"nm":"Transform"}],"nm":"Group 7"},{"ty":"gr","it":[{"ind":0,"ty":"sh","ks":{"a":0,"k":{"i":[[0,0],[0,0],[0,0],[0,0]],"o":[[0,0],[0,0],[0,0],[0,0]],"v":[[-111.127,111.12],[111.126,111.12],[111.126,-111.12],[-111.127,-111.12]],"c":true}},"nm":"Path 1"},{"ind":1,"ty":"sh","ks":{"a":0,"k":{"i":[[0,0],[0,0],[0,0],[0,0]],"o":[[0,0],[0,0],[0,0],[0,0]],"v":[[147.333,147.328],[-147.334,147.328],[-147.334,-147.328],[147.333,-147.328]],"c":true}},"nm":"Path 2"},{"ty":"mm","mm":1,"nm":"Merge Paths 1"},{"ty":"fl","c":{"a":0,"k":[0.42,0.416,0.427,1]},"o":{"a":0,"k":100},"r":1,"nm":"Fill 1"},{"ty":"tr","p":{"a":0,"k":[394.384,1518.707]},"a":{"a":0,"k":[0,0]},"s":{"a":0,"k":[100,100]},"r":{"a":0,"k":0},"o":{"a":0,"k":100},"sk":{"a":0,"k":0},"sa":{"a":0,"k":0},"nm":"Transform"}],"nm":"Group 8"},{"ty":"gr","it":[{"ind":0,"ty":"sh","ks":{"a":0,"k":{"i":[[0,0],[0,0],[0,0],[0,0]],"o":[[0,0],[0,0],[0,0],[0,0]],"v":[[553.243,24.138],[-553.242,24.138],[-553.242,-24.138],[553.243,-24.138]],"c":true}},"nm":"Path 1"},{"ty":"fl","c":{"a":0,"k":[0.42,0.416,0.427,1]},"o":{"a":0,"k":100},"r":1,"nm":"Fill 1"},{"ty":"tr","p":{"a":0,"k":[1179.49,1395.517]},"a":{"a":0,"k":[0,0]},"s":{"a":0,"k":[100,100]},"r":{"a":0,"k":0},"o":{"a":0,"k":100},"sk":{"a":0,"k":0},"sa":{"a":0,"k":0},"nm":"Transform"}],"nm":"Group 9"},{"ty":"gr","it":[{"ind":0,"ty":"sh","ks":{"a":0,"k":{"i":[[0,0],[0,0],[0,0],[0,0]],"o":[[0,0],[0,0],[0,0],[0,0]],"v":[[560.776,24.138],[-560.776,24.138],[-560.776,-24.138],[560.776,-24.138]],"c":true}},"nm":"Path 1"},{"ty":"fl","c":{"a":0,"k":[0.42,0.416,0.427,1]},"o":{"a":0,"k":100},"r":1,"nm":"Fill 1"},{"ty":"tr","p":{"a":0,"k":[1187.024,1641.896]},"a":{"a":0,"k":[0,0]},"s":{"a":0,"k":[100,100]},"r":{"a":0,"k":0},"o":{"a":0,"k":100},"sk":{"a":0,"k":0},"sa":{"a":0,"k":0},"nm":"Transform"}],"nm":"Group 10"},{"ty":"gr","it":[{"ind":0,"ty":"sh","ks":{"a":0,"k":{"i":[[0,0],[0,0],[0,0],[0,0]],"o":[[0,0],[0,0],[0,0],[0,0]],"v":[[344.693,24.138],[-344.693,24.138],[-344.693,-24.138],[344.693,-24.138]],"c":true}},"nm":"Path 1"},{"ty":"fl","c":{"a":0,"k":[0.42,0.416,0.427,1]},"o":{"a":0,"k":100},"r":1,"nm":"Fill 1"},{"ty":"tr","p":{"a":0,"k":[1365.073,907.289]},"a":{"a":0,"k":[0,0]},"s":{"a":0,"k":[100,100]},"r":{"a":0,"k":0},"o":{"a":0,"k":100},"sk":{"a":0,"k":0},"sa":{"a":0,"k":0},"nm":"Transform"}],"nm":"Group 11"},{"ty":"gr","it":[{"ind":0,"ty":"sh","ks":{"a":0,"k":{"i":[[0,0],[0,0],[0,0],[0,0]],"o":[[0,0],[0,0],[0,0],[0,0]],"v":[[344.693,24.138],[-344.693,24.138],[-344.693,-24.138],[344.693,-24.138]],"c":true}},"nm":"Path 1"},{"ty":"fl","c":{"a":0,"k":[0.42,0.416,0.427,1]},"o":{"a":0,"k":100},"r":1,"nm":"Fill 1"},{"ty":"tr","p":{"a":0,"k":[1344.023,705.061]},"a":{"a":0,"k":[0,0]},"s":{"a":0,"k":[100,100]},"r":{"a":0,"k":0},"o":{"a":0,"k":100},"sk":{"a":0,"k":0},"sa":{"a":0,"k":0},"nm":"Transform"}],"nm":"Group 12"},{"ty":"gr","it":[{"ind":0,"ty":"sh","ks":{"a":0,"k":{"i":[[0,0],[0,0],[0,0],[0,0]],"o":[[0,0],[0,0],[0,0],[0,0]],"v":[[344.693,24.138],[-344.693,24.138],[-344.693,-24.138],[344.693,-24.138]],"c":true}},"nm":"Path 1"},{"ty":"fl","c":{"a":0,"k":[0.42,0.416,0.427,1]},"o":{"a":0,"k":100},"r":1,"nm":"Fill 1"},{"ty":"tr","p":{"a":0,"k":[1326.638,502.834]},"a":{"a":0,"k":[0,0]},"s":{"a":0,"k":[100,100]},"r":{"a":0,"k":0},"o":{"a":0,"k":100},"sk":{"a":0,"k":0},"sa":{"a":0,"k":0},"nm":"Transform"}],"nm":"Group 13"},{"ty":"gr","it":[{"ind":0,"ty":"sh","ks":{"a":0,"k":{"i":[[38.425,-2.858],[0,0],[2.857,38.427],[0,0],[0,0],[0,0]],"o":[[0,0],[-38.428,2.858],[0,0],[0,0],[0,0],[2.858,38.426]],"v":[[4.946,52.078],[4.946,52.078],[-69.807,-12.326],[-72.206,-44.588],[66.949,-54.936],[69.348,-22.673]],"c":true}},"nm":"Path 1"},{"ty":"fl","c":{"a":0,"k":[0.957,0.788,0.6,1]},"o":{"a":0,"k":100},"r":1,"nm":"Fill 1"},{"ty":"tr","p":{"a":0,"k":[551.268,721.758]},"a":{"a":0,"k":[0,0]},"s":{"a":0,"k":[100,100]},"r":{"a":0,"k":0},"o":{"a":0,"k":100},"sk":{"a":0,"k":0},"sa":{"a":0,"k":0},"nm":"Transform"}],"nm":"Group 14"},{"ty":"gr","it":[{"ind":0,"ty":"sh","ks":{"a":0,"k":{"i":[[0,0],[-5.925,-15.111],[0,0],[-36.043,19.878],[0,0],[-8.618,-12.767],[0,0],[-10.127,12.875],[24.193,16.962],[103.054,-22.776],[-1.528,-25.422]],"o":[[0,0],[0,0],[0,0],[36.044,-19.878],[3.815,15.997],[0,0],[0,0],[0,0],[0,0],[-103.056,22.777],[1.53,25.421]],"v":[[-112.045,72.055],[-87.173,117.13],[-91.393,34.105],[-26.751,30.861],[77.604,-2.435],[96.648,40.446],[101.678,108.08],[116.739,59.672],[97.461,-36.743],[-17.823,-94.354],[-120.126,24.777]],"c":true}},"nm":"Path 1"},{"ty":"fl","c":{"a":0,"k":[0.208,0.204,0.204,1]},"o":{"a":0,"k":100},"r":1,"nm":"Fill 1"},{"ty":"tr","p":{"a":0,"k":[534.068,469.106]},"a":{"a":0,"k":[0,0]},"s":{"a":0,"k":[100,100]},"r":{"a":0,"k":0},"o":{"a":0,"k":100},"sk":{"a":0,"k":0},"sa":{"a":0,"k":0},"nm":"Transform"}],"nm":"Group 15"},{"ty":"gr","it":[{"ind":0,"ty":"sh","ks":{"a":0,"k":{"i":[[0,0],[-0.697,-30.435],[-10.93,-5.05],[0,0]],"o":[[-0.087,-1.166],[0.7,30.434],[10.928,5.05],[0,0]],"v":[[9.442,-9.692],[-18.566,-23.633],[8.335,49.019],[15.207,15.286]],"c":true}},"nm":"Path 1"},{"ty":"fl","c":{"a":0,"k":[0.957,0.788,0.6,1]},"o":{"a":0,"k":100},"r":1,"nm":"Fill 1"},{"ty":"tr","p":{"a":0,"k":[436.955,575.553]},"a":{"a":0,"k":[0,0]},"s":{"a":0,"k":[100,100]},"r":{"a":0,"k":0},"o":{"a":0,"k":100},"sk":{"a":0,"k":0},"sa":{"a":0,"k":0},"nm":"Transform"}],"nm":"Group 16"},{"ty":"gr","it":[{"ind":0,"ty":"sh","ks":{"a":0,"k":{"i":[[0,0],[-3.809,-30.204],[10.062,-6.611],[0,0]],"o":[[-0.087,-1.166],[3.809,30.203],[-10.061,6.611],[0,0]],"v":[[-13.717,-8.188],[11.918,-26.119],[-3.941,49.712],[-15.727,17.367]],"c":true}},"nm":"Path 1"},{"ty":"fl","c":{"a":0,"k":[0.957,0.788,0.6,1]},"o":{"a":0,"k":100},"r":1,"nm":"Fill 1"},{"ty":"tr","p":{"a":0,"k":[651.512,559.817]},"a":{"a":0,"k":[0,0]},"s":{"a":0,"k":[100,100]},"r":{"a":0,"k":0},"o":{"a":0,"k":100},"sk":{"a":0,"k":0},"sa":{"a":0,"k":0},"nm":"Transform"}],"nm":"Group 17"},{"ty":"gr","it":[{"ind":0,"ty":"sh","ks":{"a":0,"k":{"i":[[-10.504,-80.69],[56.674,-4.214],[-2.636,143.247],[-56.674,4.214]],"o":[[20.057,154.067],[-56.673,4.215],[1.498,-81.357],[56.673,-4.214]],"v":[[93.907,-77.913],[7.997,154.387],[-111.327,-62.65],[-13.856,-139.47]],"c":true}},"nm":"Path 1"},{"ty":"fl","c":{"a":0,"k":[0.957,0.788,0.6,1]},"o":{"a":0,"k":100},"r":1,"nm":"Fill 1"},{"ty":"tr","p":{"a":0,"k":[547.411,571.824]},"a":{"a":0,"k":[0,0]},"s":{"a":0,"k":[100,100]},"r":{"a":0,"k":0},"o":{"a":0,"k":100},"sk":{"a":0,"k":0},"sa":{"a":0,"k":0},"nm":"Transform"}],"nm":"Group 18"},{"ty":"gr","it":[{"ind":0,"ty":"sh","ks":{"a":0,"k":{"i":[[-184.656,-94.861],[0.24,-0.724],[9.414,-34.516],[0.242,-0.725],[3.863,-51.412],[9.413,-1.45],[127.932,5.068],[8.447,0.725],[12.553,25.099],[0.725,1.209],[0.966,1.691],[0,0]],"o":[[0,0],[-2.173,3.619],[-0.24,0.248],[-8.208,29.212],[-8.206,1.208],[-108.863,14.238],[-8.932,-0.242],[-20.519,-70.965],[-0.483,-0.966],[-0.965,-2.168],[0,0],[168.244,-121.174]],"v":[[287.606,-60.708],[287.124,-59.742],[266.123,-3.262],[265.641,-2.054],[245.364,118.637],[219.055,122.261],[-194.191,150.501],[-220.26,149.051],[-280.605,-4.706],[-282.537,-8.089],[-285.675,-13.881],[-287.607,-17.983]],"c":true}},"nm":"Path 1"},{"ty":"fl","c":{"a":0,"k":[0.898,0.227,0.286,1]},"o":{"a":0,"k":100},"r":1,"nm":"Fill 1"},{"ty":"tr","p":{"a":0,"k":[558.491,826.928]},"a":{"a":0,"k":[0,0]},"s":{"a":0,"k":[100,100]},"r":{"a":0,"k":0},"o":{"a":0,"k":100},"sk":{"a":0,"k":0},"sa":{"a":0,"k":0},"nm":"Transform"}],"nm":"Group 19"},{"ty":"gr","it":[{"ind":0,"ty":"sh","ks":{"a":0,"k":{"i":[[0,0],[8.448,0.725],[18.587,4.101],[0,0],[0,0],[0,0],[-0.965,-2.169],[-0.483,-0.966]],"o":[[-8.932,-0.242],[-23.896,-1.685],[0,0],[3.379,-14.237],[0,0],[0.967,1.691],[0.724,1.208],[0,0]],"v":[[49.484,84.242],[23.414,82.792],[-40.794,74.348],[-49.484,-62.037],[-43.932,-84.242],[-42.002,-80.14],[-38.862,-74.347],[-36.932,-70.965]],"c":true}},"nm":"Path 1"},{"ty":"fl","c":{"a":0,"k":[0.898,0.227,0.286,1]},"o":{"a":0,"k":100},"r":1,"nm":"Fill 1"},{"ty":"tr","p":{"a":0,"k":[314.817,893.187]},"a":{"a":0,"k":[0,0]},"s":{"a":0,"k":[100,100]},"r":{"a":0,"k":0},"o":{"a":0,"k":100},"sk":{"a":0,"k":0},"sa":{"a":0,"k":0},"nm":"Transform"}],"nm":"Group 20"},{"ty":"gr","it":[{"ind":0,"ty":"sh","ks":{"a":0,"k":{"i":[[2.655,-15.21],[44.656,-6.034],[9.413,-1.45],[0,0],[-0.24,0.247],[-22.69,19.553],[0,0],[-18.827,-49.962]],"o":[[0,0],[-8.206,1.208],[0,0],[0.241,-0.725],[-8.206,-18.104],[0.24,-0.725],[0,0],[0.967,40.315]],"v":[[47.793,77.24],[-24.863,87.859],[-51.173,91.484],[-4.586,-32.83],[-4.105,-34.038],[16.897,-90.518],[17.379,-91.484],[50.206,-8.934]],"c":true}},"nm":"Path 1"},{"ty":"fl","c":{"a":0,"k":[0.898,0.227,0.286,1]},"o":{"a":0,"k":100},"r":1,"nm":"Fill 1"},{"ty":"tr","p":{"a":0,"k":[828.719,857.705]},"a":{"a":0,"k":[0,0]},"s":{"a":0,"k":[100,100]},"r":{"a":0,"k":0},"o":{"a":0,"k":100},"sk":{"a":0,"k":0},"sa":{"a":0,"k":0},"nm":"Transform"}],"nm":"Group 21"},{"ty":"gr","it":[{"ind":0,"ty":"sh","ks":{"a":0,"k":{"i":[[2.655,-15.21],[44.656,-6.034],[9.413,-1.45],[127.932,5.068],[8.448,0.725],[18.587,4.102],[0,0],[0,0],[-126.725,-10.62],[-4.103,-200.825]],"o":[[0,0],[-8.206,1.208],[-108.863,14.237],[-8.933,-0.241],[-23.896,-1.686],[0,0],[0,0],[0,0],[0,0],[0.967,40.315]],"v":[[322.727,346.261],[250.071,356.88],[223.761,360.505],[-189.484,388.744],[-215.554,387.296],[-279.762,378.851],[-288.451,242.467],[-326.107,-348.194],[280.485,-383.193],[325.14,260.087]],"c":true}},"nm":"Path 1"},{"ty":"fl","c":{"a":0,"k":[0.769,0.792,0.839,1]},"o":{"a":0,"k":100},"r":1,"nm":"Fill 1"},{"ty":"tr","p":{"a":0,"k":[553.785,588.684]},"a":{"a":0,"k":[0,0]},"s":{"a":0,"k":[100,100]},"r":{"a":0,"k":0},"o":{"a":0,"k":100},"sk":{"a":0,"k":0},"sa":{"a":0,"k":0},"nm":"Transform"}],"nm":"Group 22"},{"ty":"gr","it":[{"ind":0,"ty":"sh","ks":{"a":0,"k":{"i":[[0,-2.004],[0.164,-1.368],[0.33,-0.896],[0.507,-0.4],[0.66,0],[0,0],[1.497,1.297],[0,2.947],[0,0],[-0.436,0.542],[-1.002,0.354],[-1.697,0.212],[-2.533,0],[-1.662,-0.189],[-1.002,-0.33],[-0.436,-0.519],[0,-0.66],[0,0],[0,0],[-0.495,-0.353],[-0.33,-0.848],[-0.165,-1.368]],"o":[[0,1.98],[-0.165,1.367],[-0.33,0.896],[-0.495,0.401],[0,0],[-2.204,0],[-1.497,-1.296],[0,0],[0,-0.66],[0.424,-0.519],[1.002,-0.33],[1.697,-0.189],[2.593,0],[1.673,0.212],[0.99,0.354],[0.436,0.542],[0,0],[0,0],[0.66,0],[0.507,0.377],[0.33,0.825],[0.164,1.367]],"v":[[35.523,53.969],[35.276,59.014],[34.521,62.408],[33.272,64.364],[31.528,64.954],[-27.734,64.954],[-33.285,62.997],[-35.523,56.656],[-35.523,-60.758],[-34.876,-62.573],[-32.731,-63.87],[-28.688,-64.671],[-22.336,-64.954],[-15.947,-64.671],[-11.94,-63.87],[-9.795,-62.573],[-9.147,-60.758],[-9.147,43.267],[31.528,43.267],[33.272,43.809],[34.521,45.624],[35.276,48.925]],"c":true}},"nm":"Path 1"},{"ty":"fl","c":{"a":0,"k":[0.42,0.416,0.427,1]},"o":{"a":0,"k":100},"r":1,"nm":"Fill 1"},{"ty":"tr","p":{"a":0,"k":[670.269,1174.515]},"a":{"a":0,"k":[0,0]},"s":{"a":0,"k":[100,100]},"r":{"a":0,"k":0},"o":{"a":0,"k":100},"sk":{"a":0,"k":0},"sa":{"a":0,"k":0},"nm":"Transform"}],"nm":"Group 23"},{"ty":"gr","it":[{"ind":0,"ty":"sh","ks":{"a":0,"k":{"i":[[0,-2.004],[0.165,-1.368],[0.33,-0.896],[0.507,-0.4],[0.66,0],[0,0],[1.497,1.297],[0,2.947],[0,0],[-0.436,0.542],[-1.002,0.354],[-1.698,0.212],[-2.534,0],[-1.662,-0.189],[-1.002,-0.33],[-0.436,-0.519],[0,-0.66],[0,0],[0,0],[-0.495,-0.353],[-0.33,-0.848],[-0.165,-1.368]],"o":[[0,1.98],[-0.165,1.367],[-0.33,0.896],[-0.495,0.401],[0,0],[-2.204,0],[-1.497,-1.296],[0,0],[0,-0.66],[0.424,-0.519],[1.002,-0.33],[1.697,-0.189],[2.593,0],[1.673,0.212],[0.99,0.354],[0.436,0.542],[0,0],[0,0],[0.66,0],[0.507,0.377],[0.33,0.825],[0.165,1.367]],"v":[[35.523,53.969],[35.275,59.014],[34.521,62.408],[33.272,64.364],[31.527,64.954],[-27.734,64.954],[-33.285,62.997],[-35.523,56.656],[-35.523,-60.758],[-34.876,-62.573],[-32.731,-63.87],[-28.688,-64.671],[-22.336,-64.954],[-15.947,-64.671],[-11.94,-63.87],[-9.795,-62.573],[-9.147,-60.758],[-9.147,43.267],[31.527,43.267],[33.272,43.809],[34.521,45.624],[35.275,48.925]],"c":true}},"nm":"Path 1"},{"ty":"fl","c":{"a":0,"k":[0.42,0.416,0.427,1]},"o":{"a":0,"k":100},"r":1,"nm":"Fill 1"},{"ty":"tr","p":{"a":0,"k":[583.723,1174.515]},"a":{"a":0,"k":[0,0]},"s":{"a":0,"k":[100,100]},"r":{"a":0,"k":0},"o":{"a":0,"k":100},"sk":{"a":0,"k":0},"sa":{"a":0,"k":0},"nm":"Transform"}],"nm":"Group 24"},{"ty":"gr","it":[{"ind":0,"ty":"sh","ks":{"a":0,"k":{"i":[[0,0],[0.436,-0.542],[0.99,-0.33],[1.674,-0.212],[2.593,0],[1.698,0.189],[1.002,0.33],[0.424,0.519],[0,0.684],[0,0],[-0.436,0.542],[-1.037,0.354],[-1.673,0.212],[-2.534,0],[-1.662,-0.189],[-1.002,-0.33],[-0.436,-0.519],[0,-0.66]],"o":[[0,0.684],[-0.436,0.519],[-1.002,0.33],[-1.662,0.189],[-2.534,0],[-1.697,-0.212],[-1.002,-0.33],[-0.436,-0.542],[0,0],[0,-0.66],[0.424,-0.519],[1.037,-0.33],[1.662,-0.189],[2.593,0],[1.674,0.212],[0.99,0.354],[0.436,0.542],[0,0]],"v":[[13.189,61.052],[12.541,62.868],[10.396,64.165],[6.388,64.966],[0,65.249],[-6.353,64.966],[-10.395,64.165],[-12.54,62.868],[-13.189,61.052],[-13.189,-61.052],[-12.54,-62.867],[-10.348,-64.164],[-6.294,-64.965],[0,-65.248],[6.388,-64.965],[10.396,-64.164],[12.541,-62.867],[13.189,-61.052]],"c":true}},"nm":"Path 1"},{"ty":"fl","c":{"a":0,"k":[0.42,0.416,0.427,1]},"o":{"a":0,"k":100},"r":1,"nm":"Fill 1"},{"ty":"tr","p":{"a":0,"k":[506.83,1174.81]},"a":{"a":0,"k":[0,0]},"s":{"a":0,"k":[100,100]},"r":{"a":0,"k":0},"o":{"a":0,"k":100},"sk":{"a":0,"k":0},"sa":{"a":0,"k":0},"nm":"Transform"}],"nm":"Group 25"},{"ty":"gr","it":[{"ind":0,"ty":"sh","ks":{"a":0,"k":{"i":[[0,-0.542],[0.365,-0.566],[1.037,-0.377],[1.803,-0.212],[2.723,0],[1.897,0.33],[0.837,0.66],[0.46,0.943],[0,0],[0,0],[0.401,-0.518],[0.99,-0.377],[1.673,-0.212],[2.593,0],[1.697,0.189],[1.002,0.354],[0.424,0.542],[0,0.731],[0,0],[-0.436,0.542],[-1.002,0.354],[-1.697,0.212],[-2.534,0],[-1.662,-0.189],[-1.002,-0.33],[-0.401,-0.519],[0,-0.731],[0,0],[0,0],[-0.66,0.566],[-1.072,0.33],[-1.662,0.142],[-2.605,0],[-1.732,-0.189],[-1.025,-0.353],[-0.401,-0.542],[0,-0.66],[0.601,-1.203],[1.662,-2.593],[0,0],[0,0],[-0.295,-0.919]],"o":[[0,0.731],[-0.365,0.566],[-1.025,0.354],[-1.803,0.189],[-4.337,0],[-1.898,-0.33],[-0.837,-0.684],[0,0],[0,0],[0,0.731],[-0.401,0.542],[-1.002,0.354],[-1.662,0.189],[-2.534,0],[-1.697,-0.212],[-1.002,-0.377],[-0.436,-0.518],[0,0],[0,-0.731],[0.424,-0.519],[1.002,-0.33],[1.697,-0.189],[2.593,0],[1.673,0.212],[0.99,0.354],[0.401,0.542],[0,0],[0,0],[0.46,-0.848],[0.672,-0.565],[1.061,-0.331],[1.662,-0.118],[2.664,0],[1.733,0.212],[1.037,0.377],[0.401,0.519],[0,1.131],[-0.601,1.202],[0,0],[0,0],[1.473,2.734],[0.295,0.896]],"v":[[47.216,60.769],[46.661,62.703],[44.563,64.116],[40.32,64.965],[33.531,65.248],[24.185,64.753],[20.083,63.268],[18.138,60.864],[-20.945,-0.495],[-20.945,60.864],[-21.534,62.75],[-23.632,64.116],[-27.638,64.965],[-34.026,65.248],[-40.38,64.965],[-44.422,64.116],[-46.568,62.75],[-47.216,60.864],[-47.216,-60.958],[-46.568,-62.868],[-44.422,-64.165],[-40.38,-64.966],[-34.026,-65.249],[-27.638,-64.966],[-23.632,-64.165],[-21.534,-62.868],[-20.945,-60.958],[-20.945,-5.894],[16.936,-60.865],[18.633,-63.01],[21.238,-64.353],[25.328,-65.061],[31.728,-65.249],[38.316,-64.966],[42.466,-64.118],[44.622,-62.75],[45.224,-60.958],[44.316,-57.469],[40.922,-51.766],[5.445,-5.304],[44.115,53.156],[46.767,58.625]],"c":true}},"nm":"Path 1"},{"ty":"fl","c":{"a":0,"k":[0.42,0.416,0.427,1]},"o":{"a":0,"k":100},"r":1,"nm":"Fill 1"},{"ty":"tr","p":{"a":0,"k":[428.935,1174.81]},"a":{"a":0,"k":[0,0]},"s":{"a":0,"k":[100,100]},"r":{"a":0,"k":0},"o":{"a":0,"k":100},"sk":{"a":0,"k":0},"sa":{"a":0,"k":0},"nm":"Transform"}],"nm":"Group 26"},{"ty":"gr","it":[{"ind":0,"ty":"sh","ks":{"a":0,"k":{"i":[[0,-5.186],[2.522,-5.138],[4.337,-3.441],[5.787,-1.721],[6.601,0],[3.83,0.731],[2.935,1.013],[1.968,1.131],[0.861,0.849],[0.365,1.626],[0,3.064],[-0.13,1.415],[-0.294,0.872],[-0.496,0.354],[-0.66,0],[-1.697,-1.085],[-2.663,-1.32],[-3.689,-1.108],[-4.868,0],[-2.534,0.778],[-1.768,1.414],[-0.931,2.051],[0,2.546],[1.591,2.098],[2.557,1.626],[3.265,1.438],[3.466,1.602],[3.265,2.028],[2.569,2.828],[1.603,3.866],[0,5.398],[-2.298,4.691],[-3.902,3.088],[-5.303,1.532],[-5.94,0],[-3.064,-0.448],[-2.663,-0.802],[-2.063,-0.99],[-0.659,-0.66],[-0.236,-0.448],[-0.165,-0.778],[-0.059,-1.179],[0,-1.721],[0.106,-1.344],[0.235,-0.872],[0.436,-0.401],[0.731,0],[1.603,0.943],[2.322,1.108],[3.064,0.896],[3.666,0],[2.121,-0.683],[1.426,-1.226],[0.695,-1.744],[0,-1.933],[-1.567,-2.098],[-2.628,-1.627],[-3.336,-1.415],[-3.465,-1.603],[-3.336,-2.027],[-2.593,-2.829],[-1.592,-3.842]],"o":[[0,6.789],[-2.534,5.139],[-4.326,3.418],[-5.799,1.744],[-4.455,0],[-3.831,-0.731],[-2.935,-1.037],[-1.968,-1.132],[-0.872,-0.872],[-0.366,-1.65],[0,-2.074],[0.13,-1.39],[0.307,-0.872],[0.495,-0.377],[0.931,0],[1.697,1.108],[2.664,1.344],[3.701,1.084],[3.193,0],[2.534,-0.754],[1.768,-1.391],[0.943,-2.074],[0,-2.923],[-1.603,-2.098],[-2.57,-1.627],[-3.265,-1.438],[-3.465,-1.603],[-3.264,-2.027],[-2.569,-2.829],[-1.591,-3.866],[0,-6.2],[2.299,-4.691],[3.889,-3.111],[5.293,-1.532],[3.053,0],[3.065,0.472],[2.664,0.801],[2.062,1.014],[0.672,0.683],[0.236,0.471],[0.165,0.754],[0.071,1.155],[0,1.933],[-0.095,1.32],[-0.236,0.872],[-0.436,0.401],[-0.742,0],[-1.603,-0.919],[-2.334,-1.108],[-3.065,-0.896],[-2.864,0],[-2.134,0.708],[-1.438,1.249],[-0.707,1.721],[0,2.876],[1.568,2.098],[2.628,1.65],[3.324,1.437],[3.465,1.603],[3.324,2.027],[2.604,2.828],[1.602,3.819]],"v":[[42.224,25.87],[38.429,43.762],[28.128,56.609],[12.947,64.341],[-5.652,66.958],[-18.086,65.849],[-28.234,63.21],[-35.577,59.957],[-39.82,56.963],[-41.67,53.215],[-42.224,46.167],[-42.024,40.957],[-41.376,37.562],[-40.173,35.724],[-38.429,35.158],[-34.481,36.809],[-27.928,40.462],[-18.393,44.116],[-5.545,45.766],[3.047,44.611],[9.494,41.358],[13.536,36.172],[14.939,29.265],[12.546,21.722],[6.3,16.135],[-2.446,11.539],[-12.547,6.99],[-22.636,1.544],[-31.381,-5.763],[-37.628,-15.805],[-40.02,-29.689],[-36.579,-46.026],[-27.279,-57.717],[-13.49,-64.672],[3.353,-66.958],[12.546,-66.274],[21.138,-64.365],[28.234,-61.677],[32.323,-59.178],[33.679,-57.481],[34.28,-55.62],[34.622,-52.719],[34.728,-48.382],[34.575,-43.479],[34.08,-40.179],[33.078,-38.293],[31.333,-37.68],[27.833,-39.095],[21.94,-42.135],[13.843,-45.13],[3.742,-46.474],[-3.742,-45.436],[-9.093,-42.536],[-12.287,-38.081],[-13.336,-32.589],[-10.991,-25.141],[-4.697,-19.553],[4.249,-14.956],[14.444,-10.407],[24.639,-4.962],[33.526,2.346],[39.82,12.34]],"c":true}},"nm":"Path 1"},{"ty":"fl","c":{"a":0,"k":[0.42,0.416,0.427,1]},"o":{"a":0,"k":100},"r":1,"nm":"Fill 1"},{"ty":"tr","p":{"a":0,"k":[319.4,1174.822]},"a":{"a":0,"k":[0,0]},"s":{"a":0,"k":[100,100]},"r":{"a":0,"k":0},"o":{"a":0,"k":100},"sk":{"a":0,"k":0},"sa":{"a":0,"k":0},"nm":"Transform"}],"nm":"Group 27"},{"ty":"gr","it":[{"ind":0,"ty":"sh","ks":{"a":0,"k":{"i":[[0,-1.893],[0.161,-1.27],[0.323,-0.762],[0.485,-0.369],[0.589,0],[0,0],[1.466,1.27],[0,2.886],[0,0],[-1.466,1.27],[-2.159,0],[0,0],[-0.461,-0.324],[-0.335,-0.831],[-0.161,-1.27],[0,-1.963],[0.162,-1.27],[0.323,-0.785],[0.451,-0.346],[0.588,0],[0,0],[0,0],[0,0],[-0.485,-0.346],[-0.323,-0.762],[-0.162,-1.27],[0,-1.824],[0.161,-1.247],[0.323,-0.739],[0.497,-0.323],[0.589,0],[0,0],[0,0],[0,0],[-0.485,-0.37],[-0.323,-0.785],[-0.162,-1.27]],"o":[[0,1.893],[-0.162,1.27],[-0.323,0.785],[-0.485,0.347],[0,0],[-2.159,0],[-1.466,-1.27],[0,0],[0,-2.863],[1.466,-1.27],[0,0],[0.588,0],[0.451,0.346],[0.323,0.808],[0.162,1.27],[0,1.823],[-0.161,1.293],[-0.335,0.785],[-0.461,0.37],[0,0],[0,0],[0,0],[0.589,0],[0.497,0.369],[0.323,0.738],[0.161,1.27],[0,1.893],[-0.162,1.246],[-0.323,0.762],[-0.485,0.323],[0,0],[0,0],[0,0],[0.589,0],[0.485,0.369],[0.323,0.785],[0.161,1.27]],"v":[[37.535,53.24],[37.293,57.996],[36.554,61.068],[35.33,62.798],[33.714,63.329],[-29.904,63.329],[-35.342,61.413],[-37.535,55.203],[-37.535,-55.203],[-35.342,-61.413],[-29.904,-63.329],[33.322,-63.329],[34.891,-62.845],[36.069,-61.113],[36.796,-57.996],[37.039,-53.148],[36.796,-48.507],[36.069,-45.413],[34.891,-43.705],[33.322,-43.174],[-11.896,-43.174],[-11.896,-12.236],[26.372,-12.236],[27.988,-11.705],[29.212,-10.019],[29.951,-6.995],[30.193,-2.355],[29.951,2.356],[29.212,5.333],[27.988,6.95],[26.372,7.434],[-11.896,7.434],[-11.896,43.174],[33.714,43.174],[35.33,43.705],[36.554,45.413],[37.293,48.507]],"c":true}},"nm":"Path 1"},{"ty":"fl","c":{"a":0,"k":[0.42,0.416,0.427,1]},"o":{"a":0,"k":100},"r":1,"nm":"Fill 1"},{"ty":"tr","p":{"a":0,"k":[1608.018,272.343]},"a":{"a":0,"k":[0,0]},"s":{"a":0,"k":[100,100]},"r":{"a":0,"k":0},"o":{"a":0,"k":100},"sk":{"a":0,"k":0},"sa":{"a":0,"k":0},"nm":"Transform"}],"nm":"Group 28"},{"ty":"gr","it":[{"ind":0,"ty":"sh","ks":{"a":0,"k":{"i":[[0,0],[0.357,-0.531],[0.935,-0.324],[1.57,-0.208],[2.413,0],[1.57,0.184],[0.913,0.323],[0.392,0.508],[0,0.67],[0,0],[0,0],[0,0],[0.589,-0.554],[1.016,-0.347],[1.57,-0.092],[2.217,0],[1.559,0.162],[1.004,0.346],[0.589,0.508],[0.197,0.716],[0,0],[0,0],[0,0],[0.358,-0.531],[0.981,-0.324],[1.536,-0.208],[2.413,0],[1.57,0.184],[0.947,0.323],[0.358,0.508],[0,0.67],[0,0],[-1.755,1.754],[-2.932,0],[0,0],[-2.147,-0.485],[-1.558,-1.154],[-1.05,-1.87],[-0.785,-2.747],[0,0],[0,0],[0,0],[-1.016,1.894],[-1.339,1.177],[-1.824,0.484],[-2.413,0],[0,0],[-1.269,-0.461],[-0.82,-0.877],[-0.427,-1.269],[0,-1.616]],"o":[[0,0.67],[-0.358,0.508],[-0.947,0.323],[-1.57,0.184],[-2.355,0],[-1.57,-0.208],[-0.911,-0.324],[-0.392,-0.531],[0,0],[0,0],[0,0],[-0.266,0.854],[-0.589,0.554],[-1.016,0.323],[-1.57,0.092],[-2.216,0],[-1.57,-0.162],[-1.016,-0.37],[-0.589,-0.531],[0,0],[0,0],[0,0],[0,0.67],[-0.358,0.508],[-0.97,0.323],[-1.535,0.184],[-2.355,0],[-1.558,-0.208],[-0.946,-0.324],[-0.358,-0.531],[0,0],[0,-3.325],[1.766,-1.778],[0,0],[3.001,0],[2.159,0.484],[1.57,1.131],[1.039,1.847],[0,0],[0,0],[0,0],[0.843,-2.724],[1.004,-1.893],[1.339,-1.177],[1.824,-0.485],[0,0],[1.766,0],[1.27,0.462],[0.807,0.877],[0.416,1.27],[0,0]],"v":[[73.8,59.508],[73.258,61.286],[71.307,62.557],[67.532,63.341],[61.563,63.619],[55.688,63.341],[51.97,62.557],[50.008,61.286],[49.431,59.508],[49.431,-43.556],[49.235,-43.556],[12.525,59.417],[11.255,61.517],[8.854,62.857],[4.987,63.48],[-0.693,63.619],[-6.361,63.388],[-10.228,62.603],[-12.629,61.286],[-13.807,59.417],[-49.235,-43.556],[-49.431,-43.556],[-49.431,59.508],[-49.974,61.286],[-51.982,62.557],[-55.746,63.341],[-61.668,63.619],[-67.544,63.341],[-71.307,62.557],[-73.269,61.286],[-73.8,59.508],[-73.8,-53.344],[-71.168,-60.964],[-64.115,-63.619],[-47.284,-63.619],[-39.55,-62.88],[-33.974,-60.432],[-30.049,-55.931],[-27.313,-49.027],[0.092,26.423],[0.485,26.423],[28.871,-48.842],[31.665,-55.792],[35.186,-60.386],[39.93,-62.88],[46.291,-63.619],[63.618,-63.619],[68.166,-62.926],[71.307,-60.917],[73.165,-57.685],[73.8,-53.344]],"c":true}},"nm":"Path 1"},{"ty":"fl","c":{"a":0,"k":[0.42,0.416,0.427,1]},"o":{"a":0,"k":100},"r":1,"nm":"Fill 1"},{"ty":"tr","p":{"a":0,"k":[1469.081,272.632]},"a":{"a":0,"k":[0,0]},"s":{"a":0,"k":[100,100]},"r":{"a":0,"k":0},"o":{"a":0,"k":100},"sk":{"a":0,"k":0},"sa":{"a":0,"k":0},"nm":"Transform"}],"nm":"Group 29"},{"ty":"gr","it":[{"ind":0,"ty":"sh","ks":{"a":0,"k":{"i":[[0,0],[2.274,-6.141],[4.444,-4.248],[6.522,-2.216],[8.473,0],[6.326,1.986],[4.375,4.04],[2.321,6.048],[0,8.104],[0,0],[-0.392,0.531],[-1.004,0.347],[-1.639,0.208],[-2.539,0],[-1.628,-0.184],[-0.982,-0.323],[-0.428,-0.508],[0,-0.646],[0,0],[-1.235,-3.694],[-2.308,-2.401],[-3.233,-1.2],[-3.983,0],[-3.198,1.247],[-2.217,2.378],[-1.212,3.51],[0,4.456],[0,0],[-0.392,0.531],[-0.981,0.347],[-1.662,0.208],[-2.482,0],[-1.593,-0.184],[-0.97,-0.323],[-0.392,-0.508],[0,-0.646]],"o":[[0,7.757],[-2.286,6.118],[-4.433,4.226],[-6.534,2.217],[-7.966,0],[-6.338,-1.985],[-4.375,-4.04],[-2.32,-6.026],[0,0],[0,-0.646],[0.393,-0.508],[1.016,-0.323],[1.628,-0.184],[2.482,0],[1.639,0.208],[0.969,0.347],[0.427,0.531],[0,0],[0,5.01],[1.235,3.671],[2.321,2.424],[3.232,1.224],[4.041,0],[3.198,-1.223],[2.216,-2.378],[1.2,-3.486],[0,0],[0,-0.646],[0.393,-0.508],[0.97,-0.323],[1.663,-0.184],[2.47,0],[1.605,0.208],[0.981,0.347],[0.393,0.531],[0,0]],"v":[[51.728,15.319],[48.311,36.167],[38.222,51.728],[21.783,61.402],[-0.727,64.75],[-22.164,61.748],[-38.222,52.698],[-48.254,37.576],[-51.728,16.381],[-51.728,-60.64],[-51.14,-62.418],[-49.039,-63.688],[-45.068,-64.473],[-38.811,-64.75],[-32.646,-64.473],[-28.721,-63.688],[-26.62,-62.418],[-25.986,-60.64],[-25.986,14.142],[-24.127,27.209],[-18.794,36.352],[-10.47,41.777],[0.346,43.601],[11.209,41.731],[19.336,36.306],[24.473,27.486],[26.285,15.596],[26.285,-60.64],[26.874,-62.418],[28.929,-63.688],[32.888,-64.473],[39.111,-64.75],[45.217,-64.473],[49.085,-63.688],[51.139,-62.418],[51.728,-60.64]],"c":true}},"nm":"Path 1"},{"ty":"fl","c":{"a":0,"k":[0.42,0.416,0.427,1]},"o":{"a":0,"k":100},"r":1,"nm":"Fill 1"},{"ty":"tr","p":{"a":0,"k":[1316.044,273.185]},"a":{"a":0,"k":[0,0]},"s":{"a":0,"k":[100,100]},"r":{"a":0,"k":0},"o":{"a":0,"k":100},"sk":{"a":0,"k":0},"sa":{"a":0,"k":0},"nm":"Transform"}],"nm":"Group 30"},{"ty":"gr","it":[{"ind":0,"ty":"sh","ks":{"a":0,"k":{"i":[[0,-5.079],[2.47,-5.034],[4.248,-3.371],[5.668,-1.685],[6.464,0],[3.752,0.716],[2.874,0.993],[1.928,1.108],[0.843,0.831],[0.357,1.593],[0,3.001],[-0.127,1.386],[-0.288,0.854],[-0.485,0.346],[-0.646,0],[-1.662,-1.062],[-2.609,-1.293],[-3.613,-1.085],[-4.768,0],[-2.482,0.762],[-1.732,1.385],[-0.912,2.008],[0,2.493],[1.559,2.054],[2.505,1.593],[3.197,1.408],[3.393,1.57],[3.198,1.985],[2.517,2.771],[1.57,3.786],[0,5.287],[-2.252,4.595],[-3.821,3.024],[-5.195,1.501],[-5.818,0],[-3.001,-0.439],[-2.609,-0.785],[-2.02,-0.97],[-0.646,-0.646],[-0.231,-0.439],[-0.161,-0.762],[-0.057,-1.154],[0,-1.685],[0.104,-1.316],[0.231,-0.854],[0.427,-0.392],[0.716,0],[1.57,0.924],[2.274,1.085],[3.002,0.877],[3.59,0],[2.078,-0.669],[1.397,-1.2],[0.682,-1.709],[0,-1.893],[-1.535,-2.055],[-2.574,-1.593],[-3.267,-1.385],[-3.394,-1.57],[-3.266,-1.985],[-2.54,-2.77],[-1.558,-3.764]],"o":[[0,6.649],[-2.482,5.033],[-4.237,3.347],[-5.679,1.709],[-4.364,0],[-3.752,-0.716],[-2.875,-1.016],[-1.928,-1.108],[-0.854,-0.854],[-0.358,-1.616],[0,-2.032],[0.127,-1.362],[0.3,-0.855],[0.484,-0.37],[0.912,0],[1.663,1.085],[2.609,1.315],[3.625,1.062],[3.128,0],[2.482,-0.739],[1.731,-1.362],[0.924,-2.032],[0,-2.863],[-1.569,-2.055],[-2.516,-1.593],[-3.198,-1.409],[-3.394,-1.57],[-3.198,-1.986],[-2.516,-2.77],[-1.558,-3.786],[0,-6.072],[2.251,-4.594],[3.809,-3.048],[5.183,-1.501],[2.99,0],[3.002,0.462],[2.609,0.785],[2.021,0.993],[0.658,0.67],[0.231,0.461],[0.162,0.738],[0.07,1.132],[0,1.894],[-0.092,1.293],[-0.231,0.854],[-0.427,0.393],[-0.727,0],[-1.57,-0.9],[-2.286,-1.085],[-3.001,-0.878],[-2.805,0],[-2.09,0.693],[-1.408,1.224],[-0.692,1.685],[0,2.817],[1.536,2.055],[2.574,1.616],[3.255,1.408],[3.394,1.57],[3.256,1.986],[2.551,2.771],[1.57,3.74]],"v":[[41.356,25.339],[37.639,42.863],[27.55,55.446],[12.681,63.018],[-5.535,65.581],[-17.714,64.496],[-27.653,61.91],[-34.845,58.724],[-39.001,55.792],[-40.813,52.121],[-41.356,45.218],[-41.16,40.115],[-40.525,36.791],[-39.347,34.99],[-37.639,34.436],[-33.772,36.052],[-27.353,39.631],[-18.014,43.209],[-5.431,44.825],[2.984,43.694],[9.299,40.508],[13.258,35.429],[14.632,28.664],[12.288,21.276],[6.17,15.804],[-2.395,11.302],[-12.288,6.846],[-22.17,1.513],[-30.736,-5.645],[-36.854,-15.48],[-39.197,-29.079],[-35.826,-45.079],[-26.718,-56.53],[-13.212,-63.341],[3.284,-65.581],[12.288,-64.911],[20.704,-63.041],[27.653,-60.409],[31.659,-57.962],[32.987,-56.299],[33.575,-54.475],[33.91,-51.636],[34.014,-47.388],[33.864,-42.585],[33.379,-39.353],[32.398,-37.506],[30.689,-36.906],[27.261,-38.291],[21.489,-41.269],[13.558,-44.201],[3.665,-45.517],[-3.665,-44.502],[-8.906,-41.662],[-12.035,-37.298],[-13.062,-31.919],[-10.765,-24.623],[-4.6,-19.151],[4.162,-14.649],[14.147,-10.193],[24.132,-4.86],[32.837,2.297],[39.001,12.087]],"c":true}},"nm":"Path 1"},{"ty":"fl","c":{"a":0,"k":[0.42,0.416,0.427,1]},"o":{"a":0,"k":100},"r":1,"nm":"Fill 1"},{"ty":"tr","p":{"a":0,"k":[1203.381,272.354]},"a":{"a":0,"k":[0,0]},"s":{"a":0,"k":[100,100]},"r":{"a":0,"k":0},"o":{"a":0,"k":100},"sk":{"a":0,"k":0},"sa":{"a":0,"k":0},"nm":"Transform"}],"nm":"Group 31"},{"ty":"gr","it":[{"ind":0,"ty":"sh","ks":{"a":0,"k":{"i":[[0,-1.893],[0.161,-1.27],[0.323,-0.762],[0.485,-0.369],[0.589,0],[0,0],[1.466,1.27],[0,2.886],[0,0],[-1.466,1.27],[-2.158,0],[0,0],[-0.461,-0.324],[-0.335,-0.831],[-0.161,-1.27],[0,-1.963],[0.162,-1.27],[0.323,-0.785],[0.451,-0.346],[0.589,0],[0,0],[0,0],[0,0],[-0.485,-0.346],[-0.323,-0.762],[-0.162,-1.27],[0,-1.824],[0.161,-1.247],[0.323,-0.739],[0.497,-0.323],[0.589,0],[0,0],[0,0],[0,0],[-0.485,-0.37],[-0.324,-0.785],[-0.162,-1.27]],"o":[[0,1.893],[-0.162,1.27],[-0.324,0.785],[-0.485,0.347],[0,0],[-2.158,0],[-1.466,-1.27],[0,0],[0,-2.863],[1.466,-1.27],[0,0],[0.589,0],[0.451,0.346],[0.323,0.808],[0.162,1.27],[0,1.823],[-0.161,1.293],[-0.335,0.785],[-0.461,0.37],[0,0],[0,0],[0,0],[0.589,0],[0.497,0.369],[0.323,0.738],[0.161,1.27],[0,1.893],[-0.162,1.246],[-0.323,0.762],[-0.485,0.323],[0,0],[0,0],[0,0],[0.589,0],[0.485,0.369],[0.323,0.785],[0.161,1.27]],"v":[[37.535,53.24],[37.293,57.996],[36.554,61.068],[35.33,62.798],[33.714,63.329],[-29.905,63.329],[-35.342,61.413],[-37.535,55.203],[-37.535,-55.203],[-35.342,-61.413],[-29.905,-63.329],[33.321,-63.329],[34.891,-62.845],[36.069,-61.113],[36.796,-57.996],[37.039,-53.148],[36.796,-48.507],[36.069,-45.413],[34.891,-43.705],[33.321,-43.174],[-11.896,-43.174],[-11.896,-12.236],[26.372,-12.236],[27.988,-11.705],[29.212,-10.019],[29.951,-6.995],[30.193,-2.355],[29.951,2.356],[29.212,5.333],[27.988,6.95],[26.372,7.434],[-11.896,7.434],[-11.896,43.174],[33.714,43.174],[35.33,43.705],[36.554,45.413],[37.293,48.507]],"c":true}},"nm":"Path 1"},{"ty":"fl","c":{"a":0,"k":[0.42,0.416,0.427,1]},"o":{"a":0,"k":100},"r":1,"nm":"Fill 1"},{"ty":"tr","p":{"a":0,"k":[1111.376,272.343]},"a":{"a":0,"k":[0,0]},"s":{"a":0,"k":[100,100]},"r":{"a":0,"k":0},"o":{"a":0,"k":100},"sk":{"a":0,"k":0},"sa":{"a":0,"k":0},"nm":"Transform"}],"nm":"Group 32"},{"ty":"gr","it":[{"ind":0,"ty":"sh","ks":{"a":0,"k":{"i":[[0,2.724],[1.893,2.863],[4.306,1.177],[1.663,0.184],[2.932,0],[0,0],[0,0],[0,0],[-2.747,0.877],[-1.824,1.593],[-0.912,2.217]],"o":[[0,-4.179],[-1.893,-2.886],[-1.316,-0.323],[-1.662,-0.185],[0,0],[0,0],[0,0],[3.648,0],[2.736,-0.877],[1.824,-1.593],[0.912,-2.216]],"v":[[13.801,-26.216],[10.961,-36.79],[1.668,-42.862],[-2.788,-43.647],[-9.691,-43.947],[-21.246,-43.947],[-21.246,-8.023],[-8.121,-8.023],[1.472,-9.339],[8.318,-13.056],[12.427,-18.782]],"c":true}},"nm":"Path 1"},{"ind":1,"ty":"sh","ks":{"a":0,"k":{"i":[[0,-0.647],[0.265,-0.485],[0.981,-0.323],[1.893,-0.139],[3.267,0],[1.639,0.138],[0.946,0.37],[0.38,0.554],[0.254,0.785],[0,0],[1.305,2.471],[1.604,1.662],[2.09,0.854],[2.736,0],[0,0],[0,0],[0.427,-0.531],[0.981,-0.323],[1.628,-0.208],[2.551,0],[1.663,0.184],[0.982,0.324],[0.393,0.508],[0,0.67],[0,0],[-1.466,1.27],[-2.159,0],[0,0],[-2.158,-0.138],[-1.755,-0.207],[-4.087,-1.754],[-2.839,-2.84],[-1.5,-3.879],[0,-5.01],[1.085,-3.509],[2.089,-2.725],[3.071,-2.032],[3.913,-1.246],[-1.662,-1.316],[-1.466,-1.87],[-1.304,-2.378],[-1.235,-3.002],[0,0],[-0.323,-1.131]],"o":[[0,0.715],[-0.254,0.485],[-0.97,0.324],[-1.893,0.138],[-2.736,0],[-1.628,-0.139],[-0.947,-0.346],[-0.393,-0.554],[0,0],[-1.362,-3.209],[-1.316,-2.493],[-1.593,-1.663],[-2.089,-0.831],[0,0],[0,0],[0,0.67],[-0.416,0.508],[-0.981,0.324],[-1.627,0.184],[-2.482,0],[-1.662,-0.208],[-0.969,-0.323],[-0.392,-0.531],[0,0],[0,-2.863],[1.466,-1.27],[0,0],[3.337,0],[2.148,0.116],[5.091,0.716],[4.075,1.755],[2.84,2.839],[1.501,3.902],[0,4.248],[-1.073,3.486],[-2.09,2.747],[-3.071,2.031],[1.893,0.901],[1.662,1.316],[1.466,1.847],[1.305,2.378],[0,0],[0.981,2.47],[0.324,1.155]],"v":[[46.978,59.717],[46.586,61.518],[44.727,62.741],[40.421,63.434],[32.687,63.618],[26.13,63.434],[22.263,62.695],[20.266,61.333],[19.284,59.324],[7.925,31.042],[3.919,22.522],[-0.444,16.312],[-5.974,12.525],[-13.212,11.255],[-21.246,11.255],[-21.246,59.509],[-21.881,61.287],[-23.982,62.556],[-27.896,63.342],[-34.164,63.618],[-40.375,63.342],[-44.346,62.556],[-46.401,61.287],[-46.978,59.509],[-46.978,-55.491],[-44.784,-61.702],[-39.347,-63.618],[-6.563,-63.618],[1.668,-63.411],[7.533,-62.926],[21.293,-59.209],[31.659,-52.305],[38.17,-42.239],[40.421,-28.871],[38.805,-17.258],[34.061,-7.93],[26.326,-0.773],[15.856,4.121],[21.189,7.446],[25.887,12.202],[30.043,18.551],[33.864,26.632],[44.531,51.59],[46.493,57.015]],"c":true}},"nm":"Path 2"},{"ty":"mm","mm":1,"nm":"Merge Paths 1"},{"ty":"fl","c":{"a":0,"k":[0.42,0.416,0.427,1]},"o":{"a":0,"k":100},"r":1,"nm":"Fill 1"},{"ty":"tr","p":{"a":0,"k":[1007.965,272.631]},"a":{"a":0,"k":[0,0]},"s":{"a":0,"k":[100,100]},"r":{"a":0,"k":0},"o":{"a":0,"k":100},"sk":{"a":0,"k":0},"sa":{"a":0,"k":0},"nm":"Transform"}],"nm":"Group 33"},{"ty":"gr","it":[{"ind":0,"ty":"sh","ks":{"a":0,"k":{"i":[[149.9,475.671],[24.212,1.424],[226.351,8.595],[182.44,-33.414],[-6.092,-31.967],[23.013,-1351.371],[-32.753,0],[0,0],[-0.34,32.101]],"o":[[-7.29,-23.133],[-117.365,-6.905],[-236.945,-8.998],[-32.01,5.862],[31.803,166.885],[-0.558,32.749],[0,0],[32.103,0],[3.181,-300.543]],"v":[[799.594,-1072.678],[747.188,-1113.194],[49.583,-1149.099],[-896.611,-1076.744],[-943.401,-1008.296],[-849.594,1090.437],[-791.057,1150.204],[881.589,1150.204],[940.154,1092.422]],"c":true}},"nm":"Path 1"},{"ty":"fl","c":{"a":0,"k":[0.878,0.91,0.961,1]},"o":{"a":0,"k":100},"r":1,"nm":"Fill 1"},{"ty":"tr","p":{"a":0,"k":[949.743,1158.348]},"a":{"a":0,"k":[0,0]},"s":{"a":0,"k":[100,100]},"r":{"a":0,"k":0},"o":{"a":0,"k":100},"sk":{"a":0,"k":0},"sa":{"a":0,"k":0},"nm":"Transform"}],"nm":"Group 34"}],"ip":0,"op":250,"st":0,"ct":1},{"ind":2,"ty":4,"nm":"Layer 1 Outlines","sr":1,"ks":{"o":{"a":0,"k":100},"r":{"a":0,"k":0},"p":{"a":0,"k":[1481.764,2544.403,0],"l":2},"a":{"a":0,"k":[319.034,414.441,0],"l":2},"s":{"a":0,"k":[89.674,89.674,100],"l":2}},"ao":0,"shapes":[{"ty":"gr","it":[{"ind":0,"ty":"sh","ks":{"a":0,"k":{"i":[[0,0],[0,0],[0,0],[0,0],[0,0],[0,0],[0,0],[0,0]],"o":[[0,0],[0,0],[0,0],[0,0],[0,0],[0,0],[0,0],[0,0]],"v":[[-274.595,-231.147],[-274.595,285.603],[-113.546,285.603],[-28.966,-262.43],[53.298,-262.43],[110.07,285.603],[274.595,285.603],[274.595,-285.603]],"c":true}},"nm":"Path 1"},{"ty":"fl","c":{"a":0,"k":[0.208,0.204,0.204,1]},"o":{"a":0,"k":100},"r":1,"nm":"Fill 1"},{"ty":"tr","p":{"a":0,"k":[319.372,285.853]},"a":{"a":0,"k":[0,0]},"s":{"a":0,"k":[100,100]},"r":{"a":0,"k":0},"o":{"a":0,"k":100},"sk":{"a":0,"k":0},"sa":{"a":0,"k":0},"nm":"Transform"}],"nm":"Group 1"},{"ty":"gr","it":[{"ind":0,"ty":"sh","ks":{"a":0,"k":{"i":[[1.229,-19.667],[3.072,-7.372],[1.229,-3.072],[6.151,-2.465],[19.674,0],[17.21,5.529],[4.922,10.444],[1.236,3.072],[0.607,2.465],[-17.831,23.975],[-3.079,17.831],[-6.766,2.457],[-36.277,-12.909],[-1.229,-6.758],[-22.738,-31.347]],"o":[[-0.622,9.23],[-0.614,3.072],[-4.301,11.066],[-17.21,5.529],[-19.667,0],[-6.765,-2.465],[-1.229,-3.072],[-0.614,-2.457],[-4.929,-23.353],[23.353,-31.347],[1.229,-6.758],[36.269,-12.909],[6.143,2.457],[3.079,17.831],[13.531,17.831]],"v":[[120.188,56.233],[115.265,82.058],[112.194,91.281],[95.591,112.184],[0.922,117.099],[-93.741,112.184],[-110.965,91.281],[-114.037,82.058],[-116.487,74.064],[-101.735,-4.011],[-67.309,-89.458],[-55.014,-104.21],[57.487,-104.21],[69.16,-89.458],[102.971,-4.011]],"c":true}},"nm":"Path 1"},{"ty":"fl","c":{"a":0,"k":[0.2,0.2,0.2,1]},"o":{"a":0,"k":100},"r":1,"nm":"Fill 1"},{"ty":"tr","p":{"a":0,"k":[121.666,710.919]},"a":{"a":0,"k":[0,0]},"s":{"a":0,"k":[100,100]},"r":{"a":0,"k":0},"o":{"a":0,"k":100},"sk":{"a":0,"k":0},"sa":{"a":0,"k":0},"nm":"Transform"}],"nm":"Group 2"},{"ty":"gr","it":[{"ind":0,"ty":"sh","ks":{"a":0,"k":{"i":[[0,0],[0,0],[0,0],[0,0]],"o":[[0,0],[0,0],[0,0],[0,0]],"v":[[69.318,-42.146],[61.977,109.788],[-69.318,114.404],[-56.755,-114.403]],"c":true}},"nm":"Path 1"},{"ty":"fl","c":{"a":0,"k":[0.957,0.788,0.604,1]},"o":{"a":0,"k":100},"r":1,"nm":"Fill 1"},{"ty":"tr","p":{"a":0,"k":[122.429,583.189]},"a":{"a":0,"k":[0,0]},"s":{"a":0,"k":[100,100]},"r":{"a":0,"k":0},"o":{"a":0,"k":100},"sk":{"a":0,"k":0},"sa":{"a":0,"k":0},"nm":"Transform"}],"nm":"Group 3"},{"ty":"gr","it":[{"ind":0,"ty":"sh","ks":{"a":0,"k":{"i":[[-1.229,-19.667],[-3.072,-7.372],[-1.229,-3.072],[-6.151,-2.465],[-19.674,0],[-17.21,5.529],[-4.922,10.444],[-1.236,3.072],[-0.607,2.465],[17.831,23.975],[3.079,17.831],[6.765,2.457],[36.277,-12.909],[1.229,-6.758],[22.738,-31.347]],"o":[[0.622,9.23],[0.614,3.072],[4.3,11.066],[17.21,5.529],[19.667,0],[6.765,-2.465],[1.228,-3.072],[0.615,-2.457],[4.929,-23.353],[-23.353,-31.347],[-1.229,-6.758],[-36.269,-12.909],[-6.144,2.457],[-3.079,17.831],[-13.531,17.831]],"v":[[-120.187,56.233],[-115.265,82.058],[-112.194,91.281],[-95.592,112.184],[-0.922,117.099],[93.741,112.184],[110.965,91.281],[114.036,82.058],[116.487,74.064],[101.735,-4.011],[67.309,-89.458],[55.014,-104.21],[-57.487,-104.21],[-69.16,-89.458],[-102.971,-4.011]],"c":true}},"nm":"Path 1"},{"ty":"fl","c":{"a":0,"k":[0.2,0.2,0.2,1]},"o":{"a":0,"k":100},"r":1,"nm":"Fill 1"},{"ty":"tr","p":{"a":0,"k":[516.402,710.919]},"a":{"a":0,"k":[0,0]},"s":{"a":0,"k":[100,100]},"r":{"a":0,"k":0},"o":{"a":0,"k":100},"sk":{"a":0,"k":0},"sa":{"a":0,"k":0},"nm":"Transform"}],"nm":"Group 4"},{"ty":"gr","it":[{"ind":0,"ty":"sh","ks":{"a":0,"k":{"i":[[0,0],[0,0],[0,0],[0,0]],"o":[[0,0],[0,0],[0,0],[0,0]],"v":[[-69.318,-42.146],[-61.977,109.788],[69.318,114.404],[56.755,-114.403]],"c":true}},"nm":"Path 1"},{"ty":"fl","c":{"a":0,"k":[0.957,0.788,0.604,1]},"o":{"a":0,"k":100},"r":1,"nm":"Fill 1"},{"ty":"tr","p":{"a":0,"k":[515.639,583.189]},"a":{"a":0,"k":[0,0]},"s":{"a":0,"k":[100,100]},"r":{"a":0,"k":0},"o":{"a":0,"k":100},"sk":{"a":0,"k":0},"sa":{"a":0,"k":0},"nm":"Transform"}],"nm":"Group 5"}],"ip":0,"op":250,"st":0,"ct":1}],"markers":[]}